parsetc/__init__.py
parsetc/parsetc.py
parsetc/Cantonese/extends.json
parsetc/Cantonese/mergers.json
parsetc/Cantonese/parser.py
parsetc/Cantonese/shared.lark
parsetc/Cantonese/terminals.json
parsetc/Cantonese/translit.py
parsetc/Teochew/extends.json
parsetc/Teochew/mergers.json
parsetc/Teochew/parser.py
parsetc/Teochew/shared.lark
parsetc/Teochew/terminals.json
parsetc/Teochew/translit.py
parsetc-0.4.1.dist-info/LICENSE
parsetc-0.4.1.dist-info/METADATA
parsetc-0.4.1.dist-info/WHEEL
parsetc-0.4.1.dist-info/entry_points.txt
parsetc-0.4.1.dist-info/top_level.txt
parsetc-0.4.1.dist-info/RECORD
