Metadata-Version: 2.1
Name: parsetc
Version: 0.4.1
Summary: Parse and convert between different Teochew phonetic spelling schemes.
Author: Brandon Seah
License: 
Project-URL: source, https://github.com/learn-teochew/parsetc
Project-URL: homepage, https://learn-teochew.github.io
Keywords: Chinese,Teochew,romanization
Classifier: Development Status :: 4 - Beta
Classifier: License :: OSI Approved :: MIT License
Classifier: Natural Language :: Chinese (Traditional)
Classifier: Topic :: Text Processing :: Linguistic
Requires-Python: >=3.6
License-File: LICENSE
Requires-Dist: lark ==1.1.*
Requires-Dist: importlib-resources
